cc_plugin_sgrid/__init__.py
cc_plugin_sgrid/_version.py
cc_plugin_sgrid/checker_100.py
cc_plugin_sgrid/resources/roms.nc
cc_plugin_sgrid/tests/test_checker_100.py
cc_plugin_sgrid-0.1.0.dist-info/licenses/LICENSE
cc_plugin_sgrid-0.1.0.dist-info/METADATA
cc_plugin_sgrid-0.1.0.dist-info/WHEEL
cc_plugin_sgrid-0.1.0.dist-info/entry_points.txt
cc_plugin_sgrid-0.1.0.dist-info/top_level.txt
cc_plugin_sgrid-0.1.0.dist-info/RECORD
